rload/__init__.py
rload/__main__.py
rload/cli.py
rload/event.py
rload/rload.py
rload/utils.py
rload/watcher.py
rload-0.0.2.dist-info/LICENSE
rload-0.0.2.dist-info/METADATA
rload-0.0.2.dist-info/WHEEL
rload-0.0.2.dist-info/entry_points.txt
rload-0.0.2.dist-info/top_level.txt
rload-0.0.2.dist-info/RECORD
