Metadata-Version: 2.1
Name: rload
Version: 0.0.2
Summary: A simple file monitoring with code reloader for Python 3.
Home-page: UNKNOWN
Author: Zenqi
License: MIT
Platform: UNKNOWN
Requires-Dist: hypecli (>=0.0.6)
